no_string_hints.py
no_string_hints-0.2.0.dist-info/LICENSE
no_string_hints-0.2.0.dist-info/METADATA
no_string_hints-0.2.0.dist-info/WHEEL
no_string_hints-0.2.0.dist-info/entry_points.txt
no_string_hints-0.2.0.dist-info/top_level.txt
no_string_hints-0.2.0.dist-info/RECORD
