Metadata-Version: 2.1
Name: no-string-hints
Version: 0.2.0
Summary: A tool to automatically replace string literals in type annotations.
Home-page: https://github.com/MarcoGorelli/no-string-hints
Author: Marco Gorelli
License: MIT
Platform: UNKNOWN
Classifier: License :: OSI Approved :: MIT License
Classifier: Programming Language :: Python :: 3
Classifier: Programming Language :: Python :: 3 :: Only
Classifier: Programming Language :: Python :: 3.6
Classifier: Programming Language :: Python :: 3.7
Classifier: Programming Language :: Python :: 3.8
Classifier: Programming Language :: Python :: 3.9
Classifier: Programming Language :: Python :: Implementation :: CPython
Classifier: Programming Language :: Python :: Implementation :: PyPy
Requires-Python: >=3.6.1
Requires-Dist: tokenize-rt (>=3.2.0)
